pyuefivars/__init__.py
pyuefivars/aws.py
pyuefivars/aws_file.py
pyuefivars/aws_v0.py
pyuefivars/edk2.py
pyuefivars/efivarfs.py
pyuefivars/json.py
pyuefivars/varstore.py
python_uefivars-0.1.dist-info/LICENSE
python_uefivars-0.1.dist-info/METADATA
python_uefivars-0.1.dist-info/WHEEL
python_uefivars-0.1.dist-info/entry_points.txt
python_uefivars-0.1.dist-info/top_level.txt
python_uefivars-0.1.dist-info/RECORD
